streamlit_week_selector/__init__.py
streamlit_week_selector/frontend/index.html
streamlit_week_selector/frontend/main.js
streamlit_week_selector/frontend/streamlit-component-lib.js
streamlit_week_selector/frontend/style.css
streamlit_week_selector-0.1.13.dist-info/LICENSE
streamlit_week_selector-0.1.13.dist-info/METADATA
streamlit_week_selector-0.1.13.dist-info/WHEEL
streamlit_week_selector-0.1.13.dist-info/top_level.txt
streamlit_week_selector-0.1.13.dist-info/RECORD
