Metadata-Version: 2.1
Name: streamlit-week-selector
Version: 0.1.13
Summary: this component offers you to input and choose single week from year
Author: Dmitry Usman
Author-email: dimausman@inbox.ru
Requires-Python: >=3.7
License-File: LICENSE
Requires-Dist: streamlit>=1.2
Requires-Dist: jinja2
